[
    {
        "nome": "Rodolfo Cota ",
        "apelido": "Rodolfo Cota ",
        "data_nascimento": "1987-07-03",
        "altura": 188,
        "posicao": "Goleiro",
        "pais": "México",
        "foto": "https://img.a.transfermarkt.technology/portrait/header/71401-1668452646.jpg?lm=1",
        "pe": "direito"
    },
    {
        "nome": "Guillermo Ochoa ",
        "apelido": "Guillermo Ochoa ",
        "data_nascimento": "1985-07-13",
        "altura": 185,
        "posicao": "Goleiro",
        "pais": "México",
        "foto": "https://img.a.transfermarkt.technology/portrait/header/29559-1668452843.jpg?lm=1",
        "pe": "direito"
    },
    {
        "nome": "Alfredo Talavera ",
        "apelido": "Alfredo Talavera ",
        "data_nascimento": "1982-09-18",
        "altura": 188,
        "posicao": "Goleiro",
        "pais": "México",
        "foto": "https://img.a.transfermarkt.technology/portrait/header/50965-1668452910.jpg?lm=1",
        "pe": "direito"
    },
    {
        "nome": "César Montes ",
        "apelido": "César Montes ",
        "data_nascimento": "1997-02-24",
        "altura": 191,
        "posicao": "Defensor - Zagueiro",
        "pais": "México",
        "foto": "https://img.a.transfermarkt.technology/portrait/header/387687-1666640369.jpg?lm=1",
        "pe": "direito"
    },
    {
        "nome": "Johan Vásquez ",
        "apelido": "Johan Vásquez ",
        "data_nascimento": "1998-10-22",
        "altura": 184,
        "posicao": "Defensor - Zagueiro",
        "pais": "México",
        "foto": "https://img.a.transfermarkt.technology/portrait/header/532937-1666640763.jpg?lm=1",
        "pe": "esquerdo"
    },
    {
        "nome": "Néstor Araújo ",
        "apelido": "Néstor Araújo ",
        "data_nascimento": "1991-08-29",
        "altura": 187,
        "posicao": "Defensor - Zagueiro",
        "pais": "México",
        "foto": "https://img.a.transfermarkt.technology/portrait/header/64134-1668453011.jpg?lm=1",
        "pe": "direito"
    },
    {
        "nome": "Héctor Moreno ",
        "apelido": "Héctor Moreno ",
        "data_nascimento": "1988-01-17",
        "altura": 182,
        "posicao": "Defensor - Zagueiro",
        "pais": "México",
        "foto": "https://img.a.transfermarkt.technology/portrait/header/51046-1454601493.jpg?lm=1",
        "pe": "esquerdo"
    },
    {
        "nome": "Gerardo Arteaga ",
        "apelido": "Gerardo Arteaga ",
        "data_nascimento": "1998-09-07",
        "altura": 175,
        "posicao": "Defensor - Lateral Esq.",
        "pais": "México",
        "foto": "https://img.a.transfermarkt.technology/portrait/header/469718-1666640629.jpg?lm=1",
        "pe": "esquerdo"
    },
    {
        "nome": "Jesús Gallardo ",
        "apelido": "Jesús Gallardo ",
        "data_nascimento": "1994-08-15",
        "altura": 174,
        "posicao": "Defensor - Lateral Esq.",
        "pais": "México",
        "foto": "https://img.a.transfermarkt.technology/portrait/header/344854-1668453242.jpg?lm=1",
        "pe": "esquerdo"
    },
    {
        "nome": "Jorge Sánchez ",
        "apelido": "Jorge Sánchez ",
        "data_nascimento": "1997-12-10",
        "altura": 175,
        "posicao": "Defensor - Lateral Dir.",
        "pais": "México",
        "foto": "https://img.a.transfermarkt.technology/portrait/header/356044-1668453178.jpg?lm=1",
        "pe": "direito"
    },
    {
        "nome": "Kevin Álvarez ",
        "apelido": "Kevin Álvarez ",
        "data_nascimento": "1999-01-15",
        "altura": 176,
        "posicao": "Defensor - Lateral Dir.",
        "pais": "México",
        "foto": "https://img.a.transfermarkt.technology/portrait/header/572705-1558702093.jpg?lm=1",
        "pe": "direito"
    },
    {
        "nome": "Edson Álvarez ",
        "apelido": "Edson Álvarez ",
        "data_nascimento": "1997-10-24",
        "altura": 187,
        "posicao": "Meio-Campo - Volante",
        "pais": "México",
        "foto": "https://img.a.transfermarkt.technology/portrait/header/401356-1660762574.jpg?lm=1",
        "pe": "direito"
    },
    {
        "nome": "Luis Chávez ",
        "apelido": "Luis Chávez ",
        "data_nascimento": "1996-01-15",
        "altura": 178,
        "posicao": "Meio-Campo - Volante",
        "pais": "México",
        "foto": "https://img.a.transfermarkt.technology/portrait/header/331059-1579700871.jpg?lm=1",
        "pe": "esquerdo"
    },
    {
        "nome": "Carlos Rodríguez ",
        "apelido": "Carlos Rodríguez ",
        "data_nascimento": "1997-01-03",
        "altura": 170,
        "posicao": "Meio-Campo - Meia Central",
        "pais": "México",
        "foto": "https://img.a.transfermarkt.technology/portrait/header/534620-1668453921.jpg?lm=1",
        "pe": "direito"
    },
    {
        "nome": "Érick Gutiérrez ",
        "apelido": "Érick Gutiérrez ",
        "data_nascimento": "1995-06-15",
        "altura": 176,
        "posicao": "Meio-Campo - Meia Central",
        "pais": "México",
        "foto": "https://img.a.transfermarkt.technology/portrait/header/298796-1613229788.jpg?lm=1",
        "pe": "esquerdo"
    },
    {
        "nome": "Luis Romo ",
        "apelido": "Luis Romo ",
        "data_nascimento": "1995-06-05",
        "altura": 183,
        "posicao": "Meio-Campo - Meia Central",
        "pais": "México",
        "foto": "https://img.a.transfermarkt.technology/portrait/header/532938-1580830010.jpg?lm=1",
        "pe": "direito"
    },
    {
        "nome": "Orbelín Pineda ",
        "apelido": "Orbelín Pineda ",
        "data_nascimento": "1996-03-24",
        "altura": 169,
        "posicao": "Meio-Campo - Meia Central",
        "pais": "México",
        "foto": "https://img.a.transfermarkt.technology/portrait/header/334042-1628010903.jpg?lm=1",
        "pe": "direito"
    },
    {
        "nome": "Héctor Herrera ",
        "apelido": "Héctor Herrera ",
        "data_nascimento": "1990-04-19",
        "altura": 180,
        "posicao": "Meio-Campo - Meia Central",
        "pais": "México",
        "foto": "https://img.a.transfermarkt.technology/portrait/header/122043-1668454058.jpg?lm=1",
        "pe": "direito"
    },
    {
        "nome": "Andrés Guardado ",
        "apelido": "Andrés Guardado ",
        "data_nascimento": "1986-09-28",
        "altura": 167,
        "posicao": "Meio-Campo - Meia Central",
        "pais": "México",
        "foto": "https://img.a.transfermarkt.technology/portrait/header/20506-1660318679.jpeg?lm=1",
        "pe": "esquerdo"
    },
    {
        "nome": "Alexis Vega ",
        "apelido": "Alexis Vega ",
        "data_nascimento": "1997-11-25",
        "altura": 173,
        "posicao": "Atacante - Ponta Esquerda",
        "pais": "México",
        "foto": "https://img.a.transfermarkt.technology/portrait/header/424689-1666538728.jpg?lm=1",
        "pe": "direito"
    },
    {
        "nome": "Hirving Lozano ",
        "apelido": "Hirving Lozano ",
        "data_nascimento": "1995-07-30",
        "altura": 175,
        "posicao": "Atacante - Ponta Direita",
        "pais": "México",
        "foto": "https://img.a.transfermarkt.technology/portrait/header/316889-1661508585.jpg?lm=1",
        "pe": "direito"
    },
    {
        "nome": "Roberto Alvarado ",
        "apelido": "Roberto Alvarado ",
        "data_nascimento": "1998-09-07",
        "altura": 176,
        "posicao": "Atacante - Ponta Direita",
        "pais": "México",
        "foto": "https://img.a.transfermarkt.technology/portrait/header/353583-1668454179.jpg?lm=1",
        "pe": "esquerdo"
    },
    {
        "nome": "Uriel Antuna ",
        "apelido": "Uriel Antuna ",
        "data_nascimento": "1997-08-21",
        "altura": 167,
        "posicao": "Atacante - Ponta Direita",
        "pais": "México",
        "foto": "https://img.a.transfermarkt.technology/portrait/header/355998-1550076376.JPG?lm=1",
        "pe": "direito"
    },
    {
        "nome": "Raúl Jiménez ",
        "apelido": "Raúl Jiménez ",
        "data_nascimento": "1991-05-05",
        "altura": 188,
        "posicao": "Atacante - Centroavante",
        "pais": "México",
        "foto": "https://img.a.transfermarkt.technology/portrait/header/206040-1668454631.jpg?lm=1",
        "pe": "direito"
    },
    {
        "nome": "Henry Martín ",
        "apelido": "Henry Martín ",
        "data_nascimento": "1992-11-18",
        "altura": 180,
        "posicao": "Atacante - Centroavante",
        "pais": "México",
        "foto": "https://img.a.transfermarkt.technology/portrait/header/286339-1565165533.png?lm=1",
        "pe": "direito"
    },
    {
        "nome": "Rogelio Funes Mori ",
        "apelido": "Rogelio Funes Mori ",
        "data_nascimento": "1991-03-05",
        "altura": 186,
        "posicao": "Atacante - Centroavante",
        "pais": "México",
        "foto": "https://img.a.transfermarkt.technology/portrait/header/135082-1668454750.jpg?lm=1",
        "pe": "direito"
    }
]